rna_seq_normalization/Normalization.py
rna_seq_normalization/__init__.py
rna_seq_normalization-0.3.0.dist-info/METADATA
rna_seq_normalization-0.3.0.dist-info/WHEEL
rna_seq_normalization-0.3.0.dist-info/top_level.txt
rna_seq_normalization-0.3.0.dist-info/RECORD
